Metadata-Version: 2.1
Name: exif2pandas
Version: 2.0
Summary: Extract EXIF to pandas / SQL / Excel / Feather
Home-page: https://github.com/visgean/exif2pandas
Author: Visgean
Author-email: visgean@gmail.com
License: MIT
Keywords: exif sql
Platform: UNKNOWN
Classifier: License :: OSI Approved :: MIT License
Classifier: Programming Language :: Python :: 3
Classifier: Programming Language :: Python :: 3.7
